odoo/addons/component_event/README.rst
odoo/addons/component_event/__init__.py
odoo/addons/component_event/__manifest__.py
odoo/addons/component_event/core.py
odoo/addons/component_event/components/__init__.py
odoo/addons/component_event/components/event.py
odoo/addons/component_event/i18n/component_event.pot
odoo/addons/component_event/i18n/es.po
odoo/addons/component_event/i18n/fr.po
odoo/addons/component_event/i18n/it.po
odoo/addons/component_event/i18n/zh_CN.po
odoo/addons/component_event/models/__init__.py
odoo/addons/component_event/models/base.py
odoo/addons/component_event/readme/CONTRIBUTORS.md
odoo/addons/component_event/readme/CREDITS.md
odoo/addons/component_event/readme/DESCRIPTION.md
odoo/addons/component_event/readme/HISTORY.md
odoo/addons/component_event/readme/USAGE.md
odoo/addons/component_event/static/description/icon.png
odoo/addons/component_event/static/description/index.html
odoo/addons/component_event/tests/__init__.py
odoo/addons/component_event/tests/test_event.py
odoo_addon_component_event-18.0.1.0.0.2.dist-info/METADATA
odoo_addon_component_event-18.0.1.0.0.2.dist-info/WHEEL
odoo_addon_component_event-18.0.1.0.0.2.dist-info/top_level.txt
odoo_addon_component_event-18.0.1.0.0.2.dist-info/RECORD
