Metadata-Version: 2.1
Name: odoo-addon-component_event
Version: 18.0.1.0.0.2
Requires-Python: >=3.10
Requires-Dist: cachetools
Requires-Dist: odoo-addon-component==18.0.*
Requires-Dist: odoo==18.0.*
Summary: Components Events
Home-page: https://github.com/OCA/connector
License: LGPL-3
Author: Camptocamp,Odoo Community Association (OCA)
Author-email: support@odoo-community.org
Classifier: Programming Language :: Python
Classifier: Framework :: Odoo
Classifier: Framework :: Odoo :: 18.0
Classifier: License :: OSI Approved :: GNU Lesser General Public License v3 (LGPLv3)
